cmdw/__init__.py
cmdw/__version__.py
cmdw/cmdw.py
cmdw-0.30.data/data/LICENSE.rst
cmdw-0.30.data/data/README.rst
cmdw-0.30.data/data/__version__.py
cmdw-0.30.dist-info/LICENSE.rst
cmdw-0.30.dist-info/METADATA
cmdw-0.30.dist-info/WHEEL
cmdw-0.30.dist-info/top_level.txt
cmdw-0.30.dist-info/RECORD
